PyAccessModifier/__init__.py
PyAccessModifier/modifier.py
pyaccessmodifier-0.4.3.dist-info/licenses/LICENSE
pyaccessmodifier-0.4.3.dist-info/METADATA
pyaccessmodifier-0.4.3.dist-info/WHEEL
pyaccessmodifier-0.4.3.dist-info/top_level.txt
pyaccessmodifier-0.4.3.dist-info/RECORD
