Metadata-Version: 2.4
Name: PyAccessModifier
Version: 0.4.3
Summary: Python Kotlin Acess Modifier
Author-email: howShouldIChooseMyUsername <trademark2179@gmail.com>
License: MIT
Keywords: access,capsule
License-File: LICENSE
Dynamic: license-file
